tensorgp_tf/__init__.py
tensorgp_tf/engine.py
tensorgp_tf-0.0.5.dist-info/LICENSE
tensorgp_tf-0.0.5.dist-info/METADATA
tensorgp_tf-0.0.5.dist-info/WHEEL
tensorgp_tf-0.0.5.dist-info/top_level.txt
tensorgp_tf-0.0.5.dist-info/RECORD
